setup.py
patt/__init__.py
patt/patt.py
patt.egg-info/PKG-INFO
patt.egg-info/SOURCES.txt
patt.egg-info/dependency_links.txt
patt.egg-info/not-zip-safe
patt.egg-info/requires.txt
patt.egg-info/top_level.txt