Metadata-Version: 1.0
Name: patt
Version: 1.1
Summary: lib for pattern recognition
Home-page: https://github.com/yujmo/pattern-recognition
Author: yujmo
Author-email: yujmo94@gmail.com
License: MIT License
Platform: UNKNOWN
